README.md
setup.cfg
setup.py
ssi_fc_data/__init__.py
ssi_fc_data/fc_md_client.py
ssi_fc_data/fc_md_stream.py
ssi_fc_data.egg-info/PKG-INFO
ssi_fc_data.egg-info/SOURCES.txt
ssi_fc_data.egg-info/dependency_links.txt
ssi_fc_data.egg-info/requires.txt
ssi_fc_data.egg-info/top_level.txt
ssi_fc_data/model/__init__.py
ssi_fc_data/model/access_token.py
ssi_fc_data/model/api.py
ssi_fc_data/model/constants.py
ssi_fc_data/model/model.py
ssi_fc_data/signalr/__init__.py
ssi_fc_data/signalr/_connection.py
ssi_fc_data/signalr/helpers.py
ssi_fc_data/signalr/events/__init__.py
ssi_fc_data/signalr/events/_events.py
ssi_fc_data/signalr/hubs/__init__.py
ssi_fc_data/signalr/hubs/_hub.py
ssi_fc_data/signalr/hubs/errors.py
ssi_fc_data/signalr/transports/__init__.py
ssi_fc_data/signalr/transports/_exceptions.py
ssi_fc_data/signalr/transports/_parameters.py
ssi_fc_data/signalr/transports/_queue_events.py
ssi_fc_data/signalr/transports/_transport.py
ssi_fc_data/signalr/transports/base_transport.py
ssi_fc_data/signalr/transports/connection.py
ssi_fc_data/signalr/transports/reconnection.py