Metadata-Version: 2.1
Name: ssi-fc-data
Version: 2.2.1
Summary: FastConnect Data client by Python
Home-page: https://github.com/SSI-Securities-Corporation/python-fcdata
Author: ducdv
Author-email: ducdv@ssi.com.vn
License: MIT
Platform: POSIX
Platform: Windows
Classifier: Programming Language :: Python :: 3
Classifier: License :: OSI Approved :: MIT License
Classifier: Operating System :: OS Independent
Requires-Python: >=3.5
